privadjust/__init__.py
privadjust/cli.py
privadjust/count_mean/__init__.py
privadjust/count_mean/cms_client_mean.py
privadjust/count_mean/private_cms_client.py
privadjust/count_mean/private_cms_server.py
privadjust/hadamard_count_mean/__init__.py
privadjust/hadamard_count_mean/private_hcms_client.py
privadjust/hadamard_count_mean/private_hcms_server.py
privadjust/main/__init__.py
privadjust/main/general_method.py
privadjust/main/individual_method.py
privadjust/scripts/__init__.py
privadjust/scripts/parameter_fitting.py
privadjust/scripts/preprocess.py
privadjust/scripts/server.py
privadjust/utils/__init__.py
privadjust/utils/utils.py
privadjust-1.0.13.dist-info/METADATA
privadjust-1.0.13.dist-info/WHEEL
privadjust-1.0.13.dist-info/entry_points.txt
privadjust-1.0.13.dist-info/licenses/LICENSE
privadjust-1.0.13.dist-info/RECORD
