Metadata-Version: 2.4
Name: privadjust
Version: 1.0.13
Summary: Adaptation of differential privacy algorithms applied to learning analytics.
Project-URL: Homepage, https://github.com/martaajonees/Local_Privacy
Project-URL: Issues, https://github.com/martaajonees/Local_Privacy/issues
Author-email: Marta Jones González <martajon10@gmail.com>
License-Expression: MIT
License-File: LICENSE
Classifier: Operating System :: OS Independent
Classifier: Programming Language :: Python :: 3
Requires-Python: >=3.8
Requires-Dist: colorama
Requires-Dist: matplotlib
Requires-Dist: numpy
Requires-Dist: openpyxl
Requires-Dist: optuna
Requires-Dist: pandas
Requires-Dist: progress
Requires-Dist: rich
Requires-Dist: scipy
Requires-Dist: sympy
Requires-Dist: tabulate
Requires-Dist: tqdm
